odoo/addons/project_task_material_with_sale_timesheet/README.rst
odoo/addons/project_task_material_with_sale_timesheet/__init__.py
odoo/addons/project_task_material_with_sale_timesheet/__manifest__.py
odoo/addons/project_task_material_with_sale_timesheet/i18n/project_task_material_with_sale_timesheet.pot
odoo/addons/project_task_material_with_sale_timesheet/models/__init__.py
odoo/addons/project_task_material_with_sale_timesheet/models/account_analytic.py
odoo/addons/project_task_material_with_sale_timesheet/models/project_task.py
odoo/addons/project_task_material_with_sale_timesheet/static/description/icon.png
odoo11_addon_project_task_material_with_sale_timesheet-11.0.1.0.1.dist-info/METADATA
odoo11_addon_project_task_material_with_sale_timesheet-11.0.1.0.1.dist-info/WHEEL
odoo11_addon_project_task_material_with_sale_timesheet-11.0.1.0.1.dist-info/top_level.txt
odoo11_addon_project_task_material_with_sale_timesheet-11.0.1.0.1.dist-info/RECORD
